kf_filter/__init__.py
kf_filter/consts.py
kf_filter/kf_filter.py
kf_filter/util.py
kf_filter-0.0.5.post2.dist-info/LICENSE
kf_filter-0.0.5.post2.dist-info/METADATA
kf_filter-0.0.5.post2.dist-info/WHEEL
kf_filter-0.0.5.post2.dist-info/RECORD
