Metadata-Version: 2.3
Name: kf-filter
Version: 0.0.5.post2
Summary: Filtering on the wavenumber-frequency domain based on WK99.
License: MIT
Author: Richard Zhuang
Author-email: hz542@uw.edu
Requires-Python: >=3.9,<4.0
Classifier: License :: OSI Approved :: MIT License
Classifier: Programming Language :: Python :: 3
Classifier: Programming Language :: Python :: 3.9
Classifier: Programming Language :: Python :: 3.10
Classifier: Programming Language :: Python :: 3.11
Classifier: Programming Language :: Python :: 3.12
Classifier: Programming Language :: Python :: 3.13
Requires-Dist: matplotlib (>=3.4,<4.0)
Requires-Dist: numpy (>=1.21,<2.0)
Requires-Dist: scipy (>=1.7,<2.0)
Requires-Dist: seaborn (>=0.13,<0.14)
Requires-Dist: xarray (>=2024.11.0,<2025.0.0)
